geolang/__init__.py
geolang/tests.py
geolang-0.2.2.dist-info/LICENSE.md
geolang-0.2.2.dist-info/METADATA
geolang-0.2.2.dist-info/WHEEL
geolang-0.2.2.dist-info/top_level.txt
geolang-0.2.2.dist-info/RECORD
