Metadata-Version: 2.1
Name: geolang
Version: 0.2.2
Summary: Simple Georgian Language ToolKit
Home-page: https://github.com/Lh4cKg/simple-geolang-toolkit/
Author: Lasha Gogua
Author-email: Lh4cKg@gmail.com
License: MIT
Download-URL: https://github.com/Lh4cKg/simple-geolang-toolkit/tarball/v0.2.0
Keywords: geolang,Simple,Georgian,Language,ToolKit
Platform: UNKNOWN
Classifier: Environment :: Console
Classifier: Environment :: Web Environment
Classifier: License :: OSI Approved :: Python Software Foundation License
Classifier: Operating System :: POSIX :: Linux
Classifier: Operating System :: MacOS :: MacOS X
Classifier: Operating System :: Microsoft :: Windows
Classifier: Programming Language :: Python
Classifier: Programming Language :: Python :: 3.6
Classifier: Programming Language :: Python :: 3.7
Classifier: Programming Language :: Python :: 3.8
Classifier: Topic :: Software Development :: Libraries :: Python Modules
